[
    {
        "id": 1,
        "imagenes": [
            "../imagenes/mobiliario/mesa_de_luz/1.png",
            "../imagenes/mobiliario/mesa_de_luz/2.png",
            "../imagenes/mobiliario/mesa_de_luz/3.png",
            "../imagenes/mobiliario/mesa_de_luz/4.png",
            "../imagenes/mobiliario/mesa_de_luz/5.jpg",
            "../imagenes/mobiliario/mesa_de_luz/6.jpg"
        ],
        "titulo": "Mesa de Luz",
        "linea": "Calabria",
        "modelo": "Cosenza",
        "alto": "50",
        "ancho": "45",
        "profundidad": "40",
        "materialidad": "Melamina sobre MDF",
        "cantos": "Cantos ABS 45mm",
        "herrajes": "Correderas telescopicas",
        "colores": "Blanco o Gris grafito, con Olmo Finlandes",
        "precio": 60000
    },
    {
        "id": 2,
        "imagenes": [
            "../imagenes/mobiliario/mesa-de-luz-colgante/1.png",
            "../imagenes/mobiliario/mesa-de-luz-colgante/2.png",
            "../imagenes/mobiliario/mesa-de-luz-colgante/3.png",
            "../imagenes/mobiliario/mesa-de-luz-colgante/4.png",
            "../imagenes/mobiliario/mesa-de-luz-colgante/5.jpg",
            "../imagenes/mobiliario/mesa-de-luz-colgante/6.jpg"
        ],
        "titulo": "Mesa de luz - Colgante",
        "linea": "Calabria",
        "modelo": "Crotona",
        "alto": "35",
        "ancho": "45",
        "profundidad": "40",
        "materialidad": "Melamina sobre MDF",
        "cantos": "Cantos ABS 45mm",
        "herrajes": "Correderas telescopicas",
        "colores": "Blanco o Gris grafito, con Olmo Finlandes",
        "precio": 55000
    },
    {
        "id": 3,
        "imagenes": [
            "../imagenes/mobiliario/mesa-ratona/1.png",
            "../imagenes/mobiliario/mesa-ratona/2.png",
            "../imagenes/mobiliario/mesa-ratona/3.png",
            "../imagenes/mobiliario/mesa-ratona/4.png",
            "../imagenes/mobiliario/mesa-ratona/5.jpg",
            "../imagenes/mobiliario/mesa-ratona/6.jpg"
        ],
        "titulo": "Mesa Ratona",
        "linea": "Calabria",
        "modelo": "Filandari",
        "alto": "40",
        "ancho": "80",
        "profundidad": "40",
        "materialidad": "Melamina sobre MDF",
        "cantos": "Cantos ABS 45mm",
        "herrajes": "Correderas telescopicas",
        "colores": "Blanco o Gris grafito, con Olmo Finlandes",
        "precio": 120000
    },
    {
        "id": 4,
        "imagenes": [
            "../imagenes/mobiliario/rack_de_tv/1.png",
            "../imagenes/mobiliario/rack_de_tv/2.png",
            "../imagenes/mobiliario/rack_de_tv/3.png",
            "../imagenes/mobiliario/rack_de_tv/4.png",
            "../imagenes/mobiliario/rack_de_tv/5.jpg",
            "../imagenes/mobiliario/rack_de_tv/6.jpg"
        ],
        "titulo": "Rack de TV",
        "linea": "Calabria",
        "modelo": "Cittanova",
        "alto": "50",
        "ancho": "150",
        "profundidad": "40",
        "materialidad": "Melamina sobre MDF",
        "cantos": "Cantos ABS 45mm",
        "herrajes": "Bisagras de cazoleta - Correderas telescopicas",
        "colores": "Blanco o Gris grafito, con Olmo Finlandes",
        "precio": 280000
    },
    {
        "id": 5,
        "imagenes": [
            "../imagenes/mobiliario/rack-integral/1.png",
            "../imagenes/mobiliario/rack-integral/2.png",
            "../imagenes/mobiliario/rack-integral/3.png",
            "../imagenes/mobiliario/rack-integral/4.png",
            "../imagenes/mobiliario/rack-integral/5.jpg",
            "../imagenes/mobiliario/rack-integral/6.jpg"
        ],
        "titulo": "Rack de TV integral",
        "linea": "Calabria",
        "modelo": "Cittanova",
        "alto": "50",
        "ancho": "150",
        "profundidad": "40",
        "materialidad": "Melamina sobre MDF",
        "cantos": "Cantos ABS 45mm",
        "herrajes": "Correderas telescopicas, Bisagras de cazoleta",
        "colores": "Blanco o Gris grafito, con Olmo Finlandes",
        "precio": 520000
    },
    {
        "id": 6,
        "imagenes": [
            "../imagenes/mobiliario/comoda-simple/1.png",
            "../imagenes/mobiliario/comoda-simple/2.png",
            "../imagenes/mobiliario/comoda-simple/3.png",
            "../imagenes/mobiliario/comoda-simple/4.png",
            "../imagenes/mobiliario/comoda-simple/5.jpg",
            "../imagenes/mobiliario/comoda-simple/6.jpg"
        ],
        "titulo": "Comoda un cuerpo",
        "linea": "Calabria",
        "modelo": "Crosia",
        "alto": "91",
        "ancho": "65",
        "profundidad": "40",
        "materialidad": "Melamina sobre MDF",
        "cantos": "Cantos ABS 45mm",
        "herrajes": "Correderas telescopicas",
        "colores": "Blanco o Gris grafito, con Olmo Finlandes",
        "precio": 170000
    },
    {
        "id": 7,
        "imagenes": [
            "../imagenes/mobiliario/comoda/1.png",
            "../imagenes/mobiliario/comoda/2.png",
            "../imagenes/mobiliario/comoda/3.png",
            "../imagenes/mobiliario/comoda/4.png",
            "../imagenes/mobiliario/comoda/5.jpg",
            "../imagenes/mobiliario/comoda/6.jpg"
        ],
        "titulo": "Comoda",
        "linea": "Calabria",
        "modelo": "Scalea",
        "alto": "91",
        "ancho": "130",
        "profundidad": "40",
        "materialidad": "Melamina sobre MDF",
        "cantos": "Cantos ABS 45mm",
        "herrajes": "Correderas telescopicas",
        "colores": "Blanco o Gris grafito, con Olmo Finlandes",
        "precio": 320000
    },
    {
        "id": 8,
        "imagenes": [
            "../imagenes/mobiliario/repisa/1.png",
            "../imagenes/mobiliario/repisa/2.png",
            "../imagenes/mobiliario/repisa/3.png",
            "../imagenes/mobiliario/repisa/4.png",
            "../imagenes/mobiliario/repisa/5.jpg",
            "../imagenes/mobiliario/repisa/6.jpg"
        ],
        "titulo": "Repisa",
        "linea": "Calabria",
        "modelo": "Cetraro",
        "alto": "91",
        "ancho": "60",
        "profundidad": "20",
        "materialidad": "Melamina sobre MDF",
        "cantos": "Cantos ABS 45mm",
        "herrajes": "Sin herrajes",
        "colores": "Blanco o Gris grafito, con Olmo Finlandes",
        "precio": 45000
    },
    {
        "id": 9,
        "imagenes": [
            "../imagenes/mobiliario/vajillero/1.png",
            "../imagenes/mobiliario/vajillero/2.png",
            "../imagenes/mobiliario/vajillero/3.png",
            "../imagenes/mobiliario/vajillero/4.png",
            "../imagenes/mobiliario/vajillero/5.jpg",
            "../imagenes/mobiliario/vajillero/6.jpg"
        ],
        "titulo": "Vajillero",
        "linea": "Calabria",
        "modelo": "Luzzi",
        "alto": "91",
        "ancho": "150",
        "profundidad": "40",
        "materialidad": "Melamina sobre MDF",
        "cantos": "Cantos ABS 45mm",
        "herrajes": "Bisagras de cazoleta - Correderas telescopicas",
        "colores": "Blanco o Gris grafito, con Olmo Finlandes",
        "precio": 310000
    },
    {
        "id": 10,
        "imagenes": [
            "../imagenes/mobiliario/estanteria-simple/1.png",
            "../imagenes/mobiliario/estanteria-simple/2.png",
            "../imagenes/mobiliario/estanteria-simple/3.png",
            "../imagenes/mobiliario/estanteria-simple/4.png",
            "../imagenes/mobiliario/estanteria-simple/5.jpg",
            "../imagenes/mobiliario/estanteria-simple/6.jpg"
        ],
        "titulo": "Estanteria un cuerpo",
        "linea": "Calabria",
        "modelo": "Gioia",
        "alto": "180",
        "ancho": "45",
        "profundidad": "30",
        "materialidad": "Melamina sobre MDF",
        "cantos": "Cantos ABS 45mm",
        "herrajes": "Bisagras de cazoleta",
        "colores": "Blanco o Gris grafito, con Olmo Finlandes",
        "precio": 140000
    },
    {
        "id": 11,
        "imagenes": [
            "../imagenes/mobiliario/estanteria/1.png",
            "../imagenes/mobiliario/estanteria/2.png",
            "../imagenes/mobiliario/estanteria/3.png",
            "../imagenes/mobiliario/estanteria/4.png",
            "../imagenes/mobiliario/estanteria/5.jpg",
            "../imagenes/mobiliario/estanteria/6.jpg"
        ],
        "titulo": "Estanteria",
        "linea": "Calabria",
        "modelo": "Pizzo",
        "alto": "180",
        "ancho": "86",
        "profundidad": "30",
        "materialidad": "Melamina sobre MDF",
        "cantos": "Cantos ABS 45mm",
        "herrajes": "Bisagras de cazoleta",
        "colores": "Blanco o Gris grafito, con Olmo Finlandes",
        "precio": 230000
    },
    {
        "id": 12,
        "imagenes": [
            "../imagenes/mobiliario/rack-de-tv-largo/1.png",
            "../imagenes/mobiliario/rack-de-tv-largo/2.png",
            "../imagenes/mobiliario/rack-de-tv-largo/3.png",
            "../imagenes/mobiliario/rack-de-tv-largo/4.png",
            "../imagenes/mobiliario/rack-de-tv-largo/5.jpg",
            "../imagenes/mobiliario/rack-de-tv-largo/6.jpg"
        ],
        "titulo": "Rack de TV - Largo",
        "linea": "Calabria",
        "modelo": "Soverato",
        "alto": "50",
        "ancho": "235",
        "profundidad": "40",
        "materialidad": "Melamina sobre MDF",
        "cantos": "Cantos ABS 45mm",
        "herrajes": "Correderas telescopicas, Bisagras de cazoleta",
        "colores": "Blanco o Gris grafito, con Olmo Finlandes",
        "precio": 500000
    },
    {
        "id": 13,
        "imagenes": [
            "../imagenes/mobiliario/rack-de-tv-largo-integral/1.png",
            "../imagenes/mobiliario/rack-de-tv-largo-integral/2.png",
            "../imagenes/mobiliario/rack-de-tv-largo-integral/3.png",
            "../imagenes/mobiliario/rack-de-tv-largo-integral/4.png",
            "../imagenes/mobiliario/rack-de-tv-largo-integral/5.jpg",
            "../imagenes/mobiliario/rack-de-tv-largo-integral/6.jpg"
        ],
        "titulo": "Rack de TV - Integral largo",
        "linea": "Calabria",
        "modelo": "Cassano",
        "alto": "50",
        "ancho": "235",
        "profundidad": "40",
        "materialidad": "Melamina sobre MDF",
        "cantos": "Cantos ABS 45mm",
        "herrajes": "Correderas telescopicas, Bisagras de cazoleta",
        "colores": "Blanco o Gris grafito, con Olmo Finlandes",
        "precio": 870000
    },
    {
        "id": 14,
        "imagenes": [
            "../imagenes/mobiliario/respaldo_de_cama/1.png",
            "../imagenes/mobiliario/respaldo_de_cama/2.png",
            "../imagenes/mobiliario/respaldo_de_cama/3.png",
            "../imagenes/mobiliario/respaldo_de_cama/4.png",
            "../imagenes/mobiliario/respaldo_de_cama/5.jpg",
            "../imagenes/mobiliario/respaldo_de_cama/6.jpg"
        ],
        "titulo": "Respaldo de cama",
        "linea": "Calabria",
        "modelo": "Corigliano",
        "alto": "80",
        "ancho": "240/260/300",
        "profundidad": "40",
        "materialidad": "Melamina sobre MDF",
        "cantos": "Cantos ABS 45mm",
        "herrajes": "Correderas telescopicas",
        "colores": "Blanco o Gris grafito, con Olmo Finlandes",
        "precio": 380000
    }
]